topsis/__init__.py
topsis/__main__.py
Topsis_Romil_102003290-1.0.4.dist-info/METADATA
Topsis_Romil_102003290-1.0.4.dist-info/WHEEL
Topsis_Romil_102003290-1.0.4.dist-info/entry_points.txt
Topsis_Romil_102003290-1.0.4.dist-info/top_level.txt
Topsis_Romil_102003290-1.0.4.dist-info/RECORD
