Metadata-Version: 2.1
Name: Topsis-Romil-102003290
Version: 1.0.4
Summary: topsis implementation
Home-page: 
Author: Romil Gupta
Author-email: rgupta2_be20@thapar.edu
Classifier: Programming Language :: Python :: 3
Classifier: License :: OSI Approved :: MIT License
Classifier: Operating System :: OS Independent
Requires-Python: >=3.6
